beryllium/__init__.py
beryllium/beryllium.py
beryllium/driver.py
beryllium/field.py
beryllium/listcssselector.py
beryllium/logger.py
beryllium/mongodb.py
beryllium/mysql.py
beryllium/page.py
beryllium/tabsetup.py
tests/__init__.py
tests/test1.py
beryllium-0.0.9.dist-info/LICENSE
beryllium-0.0.9.dist-info/METADATA
beryllium-0.0.9.dist-info/WHEEL
beryllium-0.0.9.dist-info/top_level.txt
beryllium-0.0.9.dist-info/RECORD
