Metadata-Version: 2.1
Name: beryllium
Version: 0.0.9
Summary: A framework for spider over selenium
Home-page: https://github.com/mannuan/beryllium
Author: mannuan
Author-email: 1271990125@qq.com
License: UNKNOWN
Platform: UNKNOWN
Classifier: Programming Language :: Python :: 3
Classifier: License :: OSI Approved :: MIT License
Classifier: Operating System :: OS Independent
Requires-Dist: selenium (>=3.14.0)
Requires-Dist: PyVirtualDisplay (>=0.2.1)
Requires-Dist: pymongo (>=3.7.1)
Requires-Dist: PyMySQL (>=0.9.2)
